sessionprofile/__init__.py
sessionprofile/apps.py
sessionprofile/middleware.py
sessionprofile/models.py
sessionprofile/py.typed
sessionprofile/settings.py
sessionprofile/signals.py
sessionprofile/backends/__init__.py
sessionprofile/backends/base.py
sessionprofile/backends/db.py
sessionprofile/management/__init__.py
sessionprofile/management/commands/__init__.py
sessionprofile/management/commands/sp_clear_expired.py
sessionprofile/migrations/0001_initial.py
sessionprofile/migrations/__init__.py
django_sessionprofile-3.0.0.dist-info/LICENSE.txt
django_sessionprofile-3.0.0.dist-info/METADATA
django_sessionprofile-3.0.0.dist-info/WHEEL
django_sessionprofile-3.0.0.dist-info/top_level.txt
django_sessionprofile-3.0.0.dist-info/RECORD
