Metadata-Version: 2.1
Name: django-sessionprofile
Version: 3.0.0
Summary: Keep track of Django user sessions
Home-page: https://github.com/modelbrouwers/django-sessionprofile
Author: Sergei Maertens
Author-email: sergei@modelbrouwers.nl
License: MIT
Project-URL: Documentation, http://django-sessionprofile.readthedocs.io/en/latest/
Project-URL: Changelog, https://github.com/modelbrouwers/django-sessionprofile/blob/main/CHANGELOG.rst
Project-URL: Bug Tracker, https://github.com/modelbrouwers/django-sessionprofile/issues
Project-URL: Source Code, https://github.com/modelbrouwers/django-sessionprofile
Keywords: django,session,user
Classifier: Development Status :: 5 - Production/Stable
Classifier: Framework :: Django
Classifier: Framework :: Django :: 3.2
Classifier: Framework :: Django :: 4.1
Classifier: Framework :: Django :: 4.2
Classifier: Intended Audience :: Developers
Classifier: Operating System :: Unix
Classifier: Operating System :: MacOS
Classifier: Operating System :: Microsoft :: Windows
Classifier: Programming Language :: Python :: 3.8
Classifier: Programming Language :: Python :: 3.9
Classifier: Programming Language :: Python :: 3.10
Classifier: Programming Language :: Python :: 3.11
Classifier: Topic :: Software Development :: Libraries :: Python Modules
License-File: LICENSE.txt
Requires-Dist: django (>=3.2)
Provides-Extra: coverage
Requires-Dist: pytest-cov ; extra == 'coverage'
Provides-Extra: docs
Requires-Dist: sphinx ; extra == 'docs'
Requires-Dist: sphinx-rtd-theme ; extra == 'docs'
Provides-Extra: pep8
Requires-Dist: flake8 ; extra == 'pep8'
Provides-Extra: release
Requires-Dist: bump2version ; extra == 'release'
Requires-Dist: twine ; extra == 'release'
Provides-Extra: tests
Requires-Dist: pytest ; extra == 'tests'
Requires-Dist: pytest-django ; extra == 'tests'
Requires-Dist: factory-boy ; extra == 'tests'
Requires-Dist: tox ; extra == 'tests'
Requires-Dist: isort ; extra == 'tests'
Requires-Dist: black ; extra == 'tests'
Requires-Dist: flake8 ; extra == 'tests'
